{"fields": [{"metadata": {}, "name": "ingested_datetime", "type": "timestamp", "nullable": false}, {"metadata": {}, "name": "expected_from", "type": "timestamp", "nullable": false}, {"metadata": {}, "name": "expected_to", "type": "timestamp", "nullable": false}, {"metadata": {}, "name": "appealrefnumber", "type": "string", "nullable": true}, {"metadata": {}, "name": "modifydate", "type": "string", "nullable": true}, {"metadata": {}, "name": "modificationentry", "type": "string", "nullable": true}, {"metadata": {}, "name": "modificationnumber", "type": "string", "nullable": true}, {"metadata": {}, "name": "dateproposedmodsadvertised", "type": "string", "nullable": true}, {"metadata": {}, "name": "dateobjectionperiodends", "type": "string", "nullable": true}, {"metadata": {}, "name": "procedureconfirmedstartdate", "type": "string", "nullable": true}, {"metadata": {}, "name": "datelocalinquiryrequested", "type": "string", "nullable": true}, {"metadata": {}, "name": "lastsittingday", "type": "string", "nullable": true}, {"metadata": {}, "name": "datetoreader", "type": "string", "nullable": true}, {"metadata": {}, "name": "datereturnedfromreader", "type": "string", "nullable": true}, {"metadata": {}, "name": "decisionorrecommendation", "type": "string", "nullable": true}, {"metadata": {}, "name": "receiptdateofdecision", "type": "string", "nullable": true}, {"metadata": {}, "name": "datedecisiondespatched", "type": "string", "nullable": true}, {"metadata": {}, "name": "reader", "type": "string", "nullable": true}]}