{
	"name": "mi_employee",
	"properties": {
		"description": "Employment Grade Descriptions",
		"content": {
			"query": "--CREATE OR ALTER VIEW mipins.vw_mipins_employee_extended\n\n--AS \n\nSelect DISTINCT Top(10)\n\n aa.PersonID\n,aa.EmployeeFirstName\n,aa.EmployeeLastName\n,aa.EmployeeName\n,aa.GenderID\n,aa.Gender\n,aa.DOB\n,aa.EmployeeNumber\n,aa.LegacyEmployeeNumber\n,aa.CivilServiceStartDate\n,aa.DateToCurrentJob\n,aa.DateToSubstantiveGrade\n,aa.SeniorityDate\n,aa.RoleStartDate\n,aa.FixTermEndDate\n,aa.LoanStartDate\n,aa.LoanEndDate\n,aa.ReasonForAction\n,aa.AnnualSalary\n,aa.Currency\n,aa.Postcode\n,aa.AddressLine1\n,aa.AddressLine2\n,aa.AddressLine3\n,aa.City\n,aa.County\n,aa.FTEPercentage\n,aa.FTE\n,aa.WorkHours\n,aa.EmploymentStatus\n,aa.PartTimeEmployee\n,aa.EmployeeGroupCode\n,aa.EmployeeGroup\n,aa.CostCenterCode\n,aa.CostCenterCentre\n,aa.PositionCode\n,aa.Position\n,aa.WorkScheduleID\n,aa.WorkScheduleRule\n,aa.WorkWeekDays\n,aa.WorkWeekHours\n,aa.WorkDayHours\n,aa.Grade\n,aa.GradeDescription\n,aa.GradeGroupV1\n,aa.GradeGroupV2\n,aa.JobCategoryShort\n,aa.JobCategory\n,aa.PersonnelAreaCode\n,aa.PersonnelArea\n,aa.PayrollAreaCode\n,aa.PayrollArea\n,aa.OrganisationalUnitCode\n,aa.OrganisationUnit\n,aa.PersonnelSubAreaCode\n,aa.PersonnelSubArea\n,aa.WorkContractCode\n,aa.WorkContract\n,aa.WorkContractType\n,aa.L1ManagerID\n,aa.L1ManagerFirstName\n,aa.L1ManagerLastName\n,aa.L1ManagerName\n,aa.L2ManagerID\n,aa.L2ManagerFirstName\n,aa.L2ManagerLastName\n,aa.L2ManagerName\n,aa.EmployeeIsActive\n,aa.EmployeeValidTo\n,aa.RoleIsActive\n,aa.RoleValidTo\n,aa.FactIsActive\n,aa.FactValidTo\n,aa.ReasonForLeaving\n,max(aa.LeaveDate) as LatestLeaveDate\n\nFROM\n\nmipins.vw_mipins_hr_employee aa\n\nGROUP BY\n\naa.PersonID\n,aa.EmployeeFirstName\n,aa.EmployeeLastName\n,aa.EmployeeName\n,aa.GenderID\n,aa.Gender\n,aa.DOB\n,aa.EmployeeNumber\n,aa.LegacyEmployeeNumber\n,aa.CivilServiceStartDate\n,aa.DateToCurrentJob\n,aa.DateToSubstantiveGrade\n,aa.SeniorityDate\n,aa.RoleStartDate\n,aa.FixTermEndDate\n,aa.LoanStartDate\n,aa.LoanEndDate\n,aa.ReasonForAction\n,aa.AnnualSalary\n,aa.Currency\n,aa.Postcode\n,aa.AddressLine1\n,aa.AddressLine2\n,aa.AddressLine3\n,aa.City\n,aa.County\n,aa.FTEPercentage\n,aa.FTE\n,aa.WorkHours\n,aa.EmploymentStatus\n,aa.PartTimeEmployee\n,aa.EmployeeGroupCode\n,aa.EmployeeGroup\n,aa.CostCenterCode\n,aa.CostCenterCentre\n,aa.PositionCode\n,aa.Position\n,aa.WorkScheduleID\n,aa.WorkScheduleRule\n,aa.WorkWeekDays\n,aa.WorkWeekHours\n,aa.WorkDayHours\n,aa.Grade\n,aa.GradeDescription\n,aa.GradeGroupV1\n,aa.GradeGroupV2\n,aa.JobCategoryShort\n,aa.JobCategory\n,aa.PersonnelAreaCode\n,aa.PersonnelArea\n,aa.PayrollAreaCode\n,aa.PayrollArea\n,aa.OrganisationalUnitCode\n,aa.OrganisationUnit\n,aa.PersonnelSubAreaCode\n,aa.PersonnelSubArea\n,aa.WorkContractCode\n,aa.WorkContract\n,aa.WorkContractType\n,aa.L1ManagerID\n,aa.L1ManagerFirstName\n,aa.L1ManagerLastName\n,aa.L1ManagerName\n,aa.L2ManagerID\n,aa.L2ManagerFirstName\n,aa.L2ManagerLastName\n,aa.L2ManagerName\n,aa.EmployeeIsActive\n,aa.EmployeeValidTo\n,aa.RoleIsActive\n,aa.RoleValidTo\n,aa.FactIsActive\n,aa.FactValidTo\n,aa.ReasonForLeaving\n\nGO",
			"metadata": {
				"language": "sql"
			},
			"currentConnection": {
				"databaseName": "odw_harmonised_db",
				"poolName": "Built-in"
			},
			"resultLimit": -1
		},
		"type": "SqlQuery"
	}
}