{
	"name": "mipins_high_court",
	"properties": {
		"description": "this is the high court view for use in either PBI or the vanilla curated view",
		"content": {
			"query": "IF NOT EXISTS ( SELECT  *\n                FROM    sys.schemas\n                WHERE   name = 'mipins' )\n    EXEC('CREATE SCHEMA [mipins]');\nGO\n\n--CREATE VIEW FOR HIGH COURT--\n\nCREATE OR ALTER VIEW mipins.vw_mipins_high_court\nAS\n\nSELECT DISTINCT\n\n*\n\nFROM [odw_harmonised_db].[dbo].high_court_dim\n\nGO",
			"metadata": {
				"language": "sql"
			},
			"currentConnection": {
				"databaseName": "odw_curated_db",
				"poolName": "Built-in"
			},
			"resultLimit": 5000
		},
		"type": "SqlQuery"
	}
}