{
	"name": "pln_saphr_main",
	"properties": {
		"activities": [
			{
				"name": "Get_SapHr_Monthly_Files",
				"type": "GetMetadata",
				"dependsOn": [
					{
						"activity": "ExecuteSapHrMonthlyFileExtract",
						"dependencyConditions": [
							"Succeeded"
						]
					}
				],
				"policy": {
					"timeout": "0.12:00:00",
					"retry": 0,
					"retryIntervalInSeconds": 30,
					"secureOutput": false,
					"secureInput": false
				},
				"userProperties": [],
				"typeProperties": {
					"dataset": {
						"referenceName": "Ds_odw_saphr_get_latest_files",
						"type": "DatasetReference",
						"parameters": {
							"Get_Load_Frequency": "MONTHLY"
						}
					},
					"fieldList": [
						"exists"
					],
					"storeSettings": {
						"type": "AzureBlobFSReadSettings",
						"recursive": true,
						"enablePartitionDiscovery": false
					},
					"formatSettings": {
						"type": "DelimitedTextReadSettings"
					}
				}
			},
			{
				"name": "If_SapHr_Monthly_Files_Exists",
				"type": "IfCondition",
				"dependsOn": [
					{
						"activity": "Get_SapHr_Monthly_Files",
						"dependencyConditions": [
							"Succeeded"
						]
					}
				],
				"userProperties": [],
				"typeProperties": {
					"expression": {
						"value": "@equals(activity('Get_SapHr_Monthly_Files').output.exists,true)",
						"type": "Expression"
					},
					"ifFalseActivities": [
						{
							"name": "Get_SapHr_Weekly_Files_Exists",
							"type": "GetMetadata",
							"dependsOn": [],
							"policy": {
								"timeout": "0.12:00:00",
								"retry": 0,
								"retryIntervalInSeconds": 30,
								"secureOutput": false,
								"secureInput": false
							},
							"userProperties": [],
							"typeProperties": {
								"dataset": {
									"referenceName": "Ds_odw_saphr_get_latest_files",
									"type": "DatasetReference",
									"parameters": {
										"Get_Load_Frequency": "WEEKLY"
									}
								},
								"fieldList": [
									"exists"
								],
								"storeSettings": {
									"type": "AzureBlobFSReadSettings",
									"recursive": true,
									"enablePartitionDiscovery": false
								},
								"formatSettings": {
									"type": "DelimitedTextReadSettings"
								}
							}
						},
						{
							"name": "Set variable1",
							"type": "SetVariable",
							"dependsOn": [
								{
									"activity": "Get_SapHr_Weekly_Files_Exists",
									"dependencyConditions": [
										"Succeeded"
									]
								}
							],
							"policy": {
								"secureOutput": false,
								"secureInput": false
							},
							"userProperties": [],
							"typeProperties": {
								"variableName": "check_folder_exists",
								"value": {
									"value": "@activity('Get_SapHr_Weekly_Files_Exists').output.exists",
									"type": "Expression"
								}
							}
						}
					],
					"ifTrueActivities": [
						{
							"name": "pln_saphr_odw_standardised_Monthly",
							"type": "ExecutePipeline",
							"dependsOn": [],
							"policy": {
								"secureInput": false
							},
							"userProperties": [],
							"typeProperties": {
								"pipeline": {
									"referenceName": "pln_saphr_standardised_master",
									"type": "PipelineReference"
								},
								"waitOnCompletion": true
							}
						}
					]
				}
			},
			{
				"name": "ExecuteSapHrWeeklyFileExtract",
				"type": "ExecutePipeline",
				"dependsOn": [],
				"policy": {
					"secureInput": false
				},
				"userProperties": [],
				"typeProperties": {
					"pipeline": {
						"referenceName": "pln_saphr_odw_source_odw_raw",
						"type": "PipelineReference"
					},
					"waitOnCompletion": true,
					"parameters": {
						"FileLoad_Type": "WEEKLY"
					}
				}
			},
			{
				"name": "ExecuteSapHrMonthlyFileExtract",
				"type": "ExecutePipeline",
				"dependsOn": [
					{
						"activity": "ExecuteSapHrWeeklyFileExtract",
						"dependencyConditions": [
							"Succeeded"
						]
					}
				],
				"policy": {
					"secureInput": false
				},
				"userProperties": [],
				"typeProperties": {
					"pipeline": {
						"referenceName": "pln_saphr_odw_source_odw_raw",
						"type": "PipelineReference"
					},
					"waitOnCompletion": true,
					"parameters": {
						"FileLoad_Type": "MONTHLY"
					}
				}
			},
			{
				"name": "If_SapHr_Weekly_Files_Exists",
				"type": "IfCondition",
				"dependsOn": [
					{
						"activity": "If_SapHr_Monthly_Files_Exists",
						"dependencyConditions": [
							"Succeeded"
						]
					}
				],
				"userProperties": [],
				"typeProperties": {
					"expression": {
						"value": "@equals(variables('check_folder_exists'),true)",
						"type": "Expression"
					},
					"ifTrueActivities": [
						{
							"name": "Wait2",
							"type": "Wait",
							"dependsOn": [],
							"userProperties": [],
							"typeProperties": {
								"waitTimeInSeconds": 1
							}
						}
					]
				}
			}
		],
		"variables": {
			"Get_File_Count": {
				"type": "String"
			},
			"check_folder_exists": {
				"type": "Boolean"
			}
		},
		"folder": {
			"name": "saphr"
		},
		"annotations": []
	}
}