{
	"name": "pln_create_lake_databases",
	"properties": {
		"activities": [
			{
				"name": "Create lake databases",
				"type": "SynapseNotebook",
				"dependsOn": [],
				"policy": {
					"timeout": "7.00:00:00",
					"retry": 0,
					"retryIntervalInSeconds": 30,
					"secureOutput": false,
					"secureInput": false
				},
				"userProperties": [],
				"typeProperties": {
					"notebook": {
						"referenceName": "py_create_lake_databases",
						"type": "NotebookReference"
					},
					"snapshot": true,
					"conf": {
						"spark.dynamicAllocation.enabled": null,
						"spark.dynamicAllocation.minExecutors": null,
						"spark.dynamicAllocation.maxExecutors": null
					},
					"numExecutors": null
				}
			}
		],
		"folder": {
			"name": "post-deployment"
		},
		"annotations": [],
		"lastPublishTime": "2022-12-12T14:23:09Z"
	},
	"type": "Microsoft.Synapse/workspaces/pipelines"
}