{
	"name": "pln_create_lake_databases",
	"properties": {
		"activities": [
			{
				"name": "Create lake databases",
				"type": "SynapseNotebook",
				"dependsOn": [],
				"policy": {
					"timeout": "7.00:00:00",
					"retry": 0,
					"retryIntervalInSeconds": 30,
					"secureOutput": false,
					"secureInput": false
				},
				"userProperties": [],
				"typeProperties": {
					"notebook": {
						"referenceName": "py_create_lake_databases",
						"type": "NotebookReference"
					},
					"snapshot": true,
					"conf": {
						"spark.dynamicAllocation.enabled": null,
						"spark.dynamicAllocation.minExecutors": null,
						"spark.dynamicAllocation.maxExecutors": null
					},
					"numExecutors": null
				}
			},
			{
				"name": "0_Legacy_Timesheet_Data_Copy_RAW",
				"type": "ExecutePipeline",
				"dependsOn": [],
				"userProperties": [],
				"typeProperties": {
					"pipeline": {
						"referenceName": "0_Legacy_Timesheet_Data_Copy_RAW",
						"type": "PipelineReference"
					},
					"waitOnCompletion": true
				}
			},
			{
				"name": "0_pln_source_to_raw_MiPINS",
				"type": "ExecutePipeline",
				"dependsOn": [],
				"userProperties": [],
				"typeProperties": {
					"pipeline": {
						"referenceName": "0_pln_source_to_raw_MiPINS",
						"type": "PipelineReference"
					},
					"waitOnCompletion": true
				}
			},
			{
				"name": "py_1_raw_to_standardised_scheduling",
				"type": "SynapseNotebook",
				"dependsOn": [
					{
						"activity": "Create lake databases",
						"dependencyConditions": [
							"Succeeded"
						]
					},
					{
						"activity": "0_Legacy_Timesheet_Data_Copy_RAW",
						"dependencyConditions": [
							"Succeeded"
						]
					},
					{
						"activity": "0_pln_source_to_raw_MiPINS",
						"dependencyConditions": [
							"Succeeded"
						]
					}
				],
				"policy": {
					"timeout": "0.12:00:00",
					"retry": 0,
					"retryIntervalInSeconds": 30,
					"secureOutput": false,
					"secureInput": false
				},
				"userProperties": [],
				"typeProperties": {
					"notebook": {
						"referenceName": "py_1_raw_to_standardised_scheduling",
						"type": "NotebookReference"
					},
					"snapshot": true
				}
			}
		],
		"folder": {
			"name": "post-deployment"
		},
		"annotations": [],
		"lastPublishTime": "2023-01-19T12:53:30Z"
	},
	"type": "Microsoft.Synapse/workspaces/pipelines"
}